yaqd_mqtt/VERSION
yaqd_mqtt/__init__.py
yaqd_mqtt/__version__.py
yaqd_mqtt/_mqtt_homie_sensor.py
yaqd_mqtt/mqtt-homie-sensor.avpr
yaqd_mqtt/mqtt-homie-sensor.toml
yaqd_mqtt-2021.3.1.dist-info/entry_points.txt
yaqd_mqtt-2021.3.1.dist-info/LICENSE
yaqd_mqtt-2021.3.1.dist-info/WHEEL
yaqd_mqtt-2021.3.1.dist-info/METADATA
yaqd_mqtt-2021.3.1.dist-info/RECORD
