Metadata-Version: 2.1
Name: yaqd-mqtt
Version: 2021.3.1
Summary: yaq daemons for interacting with MQTT brokers
Home-page: https://yaq.fyi
License: UNKNOWN
Author: Blaise Thompson
Author-email: blaise@untzag.com
Requires-Python: >=3.7
Classifier: Development Status :: 2 - Pre-Alpha
Classifier: Intended Audience :: Science/Research
Classifier: License :: OSI Approved :: GNU Lesser General Public License v3 (LGPLv3)
Classifier: Natural Language :: English
Classifier: Programming Language :: Python :: 3
Classifier: Programming Language :: Python :: 3.7
Classifier: Programming Language :: Python :: 3.8
Classifier: Topic :: Scientific/Engineering
Requires-Dist: yaqd-core>=2021.3.0
Requires-Dist: paho-mqtt
Requires-Dist: black ; extra == "dev"
Requires-Dist: pre-commit ; extra == "dev"
Project-URL: Issues, https://gitlab.com/yaq/yaqd-mqtt/issues
Project-URL: Source, https://gitlab.com/yaq/yaqd-mqtt
Provides-Extra: dev
